[
    {
      "op": "remove",
      "file": "fantasycreatures:entities/land/treant",
      "path": "/server/behaviors/7/dropsByType/treant-walnut/0",
      "side": "Server"
    },
    {
      "op": "remove",
      "file": "fantasycreatures:entities/land/treant",
      "path": "/server/behaviors/7/dropsByType/treant-oak/0",
      "side": "Server"
    },
    {
      "op": "remove",
      "file": "fantasycreatures:entities/land/treant",
      "path": "/server/behaviors/7/dropsByType/treant-pine/0",
      "side": "Server"
    }
]